bl2_skingen/argparse_formatter.py
bl2_skingen/argparser.py
bl2_skingen/decalspec.py
bl2_skingen/flags.py
bl2_skingen/log_formatter.py
bl2_skingen/props.py
bl2_skingen/skingen.py
bl2_skingen/unreal_notation.py
bl2_skingen/imaging/apply_decal.cp38-win_amd64.pyd
bl2_skingen/imaging/blend_inplace.cp38-win_amd64.pyd
bl2_skingen/imaging/darken.cp38-win_amd64.pyd
bl2_skingen/imaging/multiply_sqrt.cp38-win_amd64.pyd
bl2_skingen/imaging/overlay.cp38-win_amd64.pyd
bl2_skingen/imaging/ue_color_diff.cp38-win_amd64.pyd
BL2_skingen-1.4.0.dist-info/LICENSE
BL2_skingen-1.4.0.dist-info/METADATA
BL2_skingen-1.4.0.dist-info/WHEEL
BL2_skingen-1.4.0.dist-info/entry_points.txt
BL2_skingen-1.4.0.dist-info/top_level.txt
BL2_skingen-1.4.0.dist-info/RECORD
