Metadata-Version: 2.1
Name: BL2-skingen
Version: 1.4.0
Summary: Utility to generate png files from Borderlands 2 in-game skin files.
Home-page: https://www.github.com/Square789/BL2_skingen/
License: UNKNOWN
Platform: UNKNOWN
Classifier: License :: OSI Approved :: MIT License
Classifier: Natural Language :: English
Classifier: Operating System :: Microsoft :: Windows
Classifier: Programming Language :: Cython
Classifier: Programming Language :: Python
Classifier: Topic :: Multimedia :: Graphics :: Graphics Conversion
Requires-Dist: numpy
Requires-Dist: Pillow
Requires-Dist: Cython
